intellisys/__init__.py
intellisys/intellisys.py
intellisys-0.1.8.dist-info/LICENSE
intellisys-0.1.8.dist-info/METADATA
intellisys-0.1.8.dist-info/WHEEL
intellisys-0.1.8.dist-info/top_level.txt
intellisys-0.1.8.dist-info/RECORD
