Metadata-Version: 2.1
Name: intellisys
Version: 0.1.8
Summary: Intelligence/AI services for the Lifsys Enterprise
Home-page: https://github.com/yourusername/intellisys
Author: Mark Powers
Author-email: Lifsys Enterprise <contact@lifsys.com>
License: MIT License
Project-URL: Homepage, https://github.com/lifsys/intellisys
Project-URL: Documentation, https://intellisys.readthedocs.io/
Project-URL: Repository, https://github.com/lifsys/intellisys.git
Project-URL: Bug Tracker, https://github.com/lifsys/intellisys/issues
Keywords: ai,intelligence,openai,anthropic,google
Classifier: Development Status :: 3 - Alpha
Classifier: Intended Audience :: Developers
Classifier: License :: OSI Approved :: MIT License
Classifier: Operating System :: OS Independent
Classifier: Programming Language :: Python :: 3
Classifier: Programming Language :: Python :: 3.7
Classifier: Programming Language :: Python :: 3.8
Classifier: Programming Language :: Python :: 3.9
Classifier: Programming Language :: Python :: 3.10
Classifier: Programming Language :: Python :: 3.11
Requires-Python: >=3.6
License-File: LICENSE
Requires-Dist: openai >=1.0.0
Requires-Dist: litellm >=1.0.0
Requires-Dist: jinja2 >=3.0.0
Requires-Dist: onepasswordconnectsdk >=1.0.0
Provides-Extra: dev
Requires-Dist: pytest >=6.0 ; extra == 'dev'
Requires-Dist: pytest-cov >=2.0 ; extra == 'dev'
Requires-Dist: flake8 >=3.9 ; extra == 'dev'
Requires-Dist: black >=21.5b1 ; extra == 'dev'
